AaronTools/LICENSE
AaronTools/README.md
AaronTools/__init__.py
AaronTools/atoms.py
AaronTools/calculated_bond_lengths.json
AaronTools/comp_output.py
AaronTools/component.py
AaronTools/config.ini
AaronTools/config.py
AaronTools/const.py
AaronTools/fileIO.py
AaronTools/finders.py
AaronTools/geometry.py
AaronTools/internal_coordinates.py
AaronTools/job_control.py
AaronTools/json_extension.py
AaronTools/new_fileIO.py
AaronTools/oniomatoms.py
AaronTools/orbitals.py
AaronTools/pathway.py
AaronTools/ring.py
AaronTools/spectra.py
AaronTools/substituent.py
AaronTools/symmetry.py
AaronTools/AaronTools.egg-info/PKG-INFO
AaronTools/AaronTools.egg-info/SOURCES.txt
AaronTools/AaronTools.egg-info/dependency_links.txt
AaronTools/AaronTools.egg-info/requires.txt
AaronTools/AaronTools.egg-info/top_level.txt
AaronTools/Ligands/ACN.xyz
AaronTools/Ligands/AcAc.xyz
AaronTools/Ligands/Ad-HC5C.xyz
AaronTools/Ligands/BDA.xyz
AaronTools/Ligands/BPE.xyz
AaronTools/Ligands/BPY.xyz
AaronTools/Ligands/BenQuin.xyz
AaronTools/Ligands/BiOX.xyz
AaronTools/Ligands/BiOx_Me.xyz
AaronTools/Ligands/CO.xyz
AaronTools/Ligands/COD.xyz
AaronTools/Ligands/Cp.xyz
AaronTools/Ligands/Cp_star.xyz
AaronTools/Ligands/DMBPY.xyz
AaronTools/Ligands/DMP.xyz
AaronTools/Ligands/DMPE.xyz
AaronTools/Ligands/DPEphos.xyz
AaronTools/Ligands/DPPE.xyz
AaronTools/Ligands/DPPF.xyz
AaronTools/Ligands/DPPP.xyz
AaronTools/Ligands/EDA.xyz
AaronTools/Ligands/IMes.xyz
AaronTools/Ligands/JoshPhos.xyz
AaronTools/Ligands/KASBAI.xyz
AaronTools/Ligands/Mes-NC5C.xyz
AaronTools/Ligands/Milstein.xyz
AaronTools/Ligands/NBD.xyz
AaronTools/Ligands/PHNNP.xyz
AaronTools/Ligands/PIN.xyz
AaronTools/Ligands/PPh3.xyz
AaronTools/Ligands/Paton_DL.xyz
AaronTools/Ligands/Paton_EL.xyz
AaronTools/Ligands/PhBP3.xyz
AaronTools/Ligands/PymdOx.xyz
AaronTools/Ligands/PyrOx.xyz
AaronTools/Ligands/R-BINAP.xyz
AaronTools/Ligands/R-Me-StackPhos.xyz
AaronTools/Ligands/R-Ph-BOX.xyz
AaronTools/Ligands/R-Ph-Mes-NC5C.xyz
AaronTools/Ligands/R-Quinox-AdtBu2.xyz
AaronTools/Ligands/R-Quinox-tBu3.xyz
AaronTools/Ligands/R-SEGPHOS.xyz
AaronTools/Ligands/R-StackPhos.xyz
AaronTools/Ligands/R-iPr-PyBOX.xyz
AaronTools/Ligands/R-pFPh-StackPhos.xyz
AaronTools/Ligands/R-tBu-BOX.xyz
AaronTools-1.1.dist-info/LICENSE
AaronTools-1.1.dist-info/METADATA
AaronTools-1.1.dist-info/WHEEL
AaronTools-1.1.dist-info/top_level.txt
AaronTools-1.1.dist-info/RECORD
