Metadata-Version: 2.1
Name: AaronTools
Version: 1.1
Summary: Tools for measuring and manipulating molecular structures
Home-page: https://github.com/QChASM/AaronTools.py
Author: QChASM
Author-email: qchasm@uga.edu
Project-URL: Bug Reports, https://github.com/QChASM/AaronTools.py/issues
Project-URL: Source, https://github.com/QChASM/AaronTools.py
Keywords: computational chemistry utility
Classifier: Development Status :: 4 - Beta
Classifier: Intended Audience :: Science/Research
Classifier: Topic :: Scientific/Engineering :: Chemistry
Classifier: License :: OSI Approved :: GNU General Public License v3 (GPLv3)
Classifier: Programming Language :: Python :: 3
Classifier: Programming Language :: Python :: 3.5
Classifier: Programming Language :: Python :: 3.6
Classifier: Programming Language :: Python :: 3.7
Classifier: Programming Language :: Python :: 3.8
Classifier: Programming Language :: Python :: 3.9
Classifier: Programming Language :: Python :: 3.10
Requires-Python: >=3.5, <4
License-File: LICENSE
Requires-Dist: numpy
Requires-Dist: scipy
Provides-Extra: extras
Requires-Dist: pdfminer ; extra == 'extras'
Requires-Dist: jinja2 ; extra == 'extras'
Requires-Dist: matplotlib ; extra == 'extras'
